orjson/__init__.py
orjson/__init__.pyi
orjson/orjson.cpython-311-aarch64-linux-musl.so
orjson/py.typed
orjson-3.11.6.dist-info/METADATA
orjson-3.11.6.dist-info/WHEEL
orjson-3.11.6.dist-info/licenses/LICENSE-APACHE
orjson-3.11.6.dist-info/licenses/LICENSE-MIT
orjson-3.11.6.dist-info/licenses/LICENSE-MPL-2.0
orjson-3.11.6.dist-info/RECORD
