Metadata-Version: 2.4
Name: orjson
Version: 3.11.6
Classifier: Development Status :: 5 - Production/Stable
Classifier: Intended Audience :: Developers
Classifier: License :: OSI Approved :: Apache Software License
Classifier: License :: OSI Approved :: MIT License
Classifier: License :: OSI Approved :: Mozilla Public License 2.0 (MPL 2.0)
Classifier: Operating System :: MacOS
Classifier: Operating System :: Microsoft :: Windows
Classifier: Operating System :: POSIX :: Linux
Classifier: Programming Language :: Python :: 3
Classifier: Programming Language :: Python :: 3.10
Classifier: Programming Language :: Python :: 3.11
Classifier: Programming Language :: Python :: 3.12
Classifier: Programming Language :: Python :: 3.13
Classifier: Programming Language :: Python :: 3.14
Classifier: Programming Language :: Python :: 3.15
Classifier: Programming Language :: Python :: Implementation :: CPython
Classifier: Programming Language :: Python
Classifier: Programming Language :: Rust
Classifier: Typing :: Typed
License-File: LICENSE-APACHE
License-File: LICENSE-MIT
License-File: LICENSE-MPL-2.0
Summary: Fast, correct Python JSON library supporting dataclasses, datetimes, and numpy
License-Expression: MPL-2.0 AND (Apache-2.0 OR MIT)
Requires-Python: >=3.10
Project-URL: changelog, https://github.com/ijl/orjson/blob/master/CHANGELOG.md
Project-URL: documentation, https://github.com/ijl/orjson
Project-URL: source, https://github.com/ijl/orjson
